aws_lambda_proxy/__init__.py
aws_lambda_proxy/proxy.py
aws_lambda_proxy/py.typed
aws_lambda_proxy/templates.py
aws_lambda_proxy/types.py
aws_lambda_proxy-1.1.1.dist-info/licenses/LICENSE.txt
aws_lambda_proxy-1.1.1.dist-info/METADATA
aws_lambda_proxy-1.1.1.dist-info/WHEEL
aws_lambda_proxy-1.1.1.dist-info/top_level.txt
aws_lambda_proxy-1.1.1.dist-info/RECORD
