Metadata-Version: 2.4
Name: aws-lambda-proxy
Version: 1.1.1
Summary: Simple AWS Lambda proxy to handle API Gateway request
Author-email: Lucas Messenger <1335960+layertwo@users.noreply.github.com>
License: BSD
Keywords: aws,lambda,apigateway,proxy
Classifier: Programming Language :: Python :: 3
Classifier: Programming Language :: Python :: 3.9
Classifier: Programming Language :: Python :: 3.10
Classifier: Programming Language :: Python :: 3.11
Classifier: Programming Language :: Python :: 3.12
Classifier: Programming Language :: Python :: 3.13
Classifier: License :: OSI Approved :: MIT License
Classifier: Operating System :: OS Independent
Requires-Python: >=3.9
License-File: LICENSE.txt
Provides-Extra: test
Requires-Dist: pytest==8.4.2; extra == "test"
Requires-Dist: pytest-cov==7.0.0; extra == "test"
Requires-Dist: black==25.1.0; extra == "test"
Requires-Dist: isort==6.0.1; extra == "test"
Requires-Dist: flake8==7.3.0; extra == "test"
Requires-Dist: Flake8-pyproject==1.2.3; extra == "test"
Dynamic: license-file
